{
    "Solaflex": "jan.waechter@baloise.com",
    "joachimprinzbach": "joachim.prinzbach@baloise.ch",
    "Resurrectum": "rafael.kluender@baloise.ch",
    "FilipMarkovski": "filip.markovski@baloise.ch",
    "girafi": "raffael.heinzer@baloise.ch",
    "niiku": "nikolas.philips@baloise.com",
    "PhilippBal": "Philipp.Albert@baloise.ch",
    "lulevapa": "Patrick.Brack@baloise.com",
    "greg-junkietech": "Gregory.Laplace@baloise.ch",
    "lutzifer777": "Andreas.Lutz@baloise.ch",
    "TM2025": "timo.metzing@baloise.ch",
    "Floinker": "Timo.Sickinger@baloise.ch",
    "dweber019": "david.weber@baloise.ch",
    "KamilWiecek": "Kamil.Wiecek@baloise.com",
    "silvansievers": "silvan.sievers@baloise.ch"
}
